{"name": "РПК-74", "info": [{"key": "Ранг", "value": "Ветеран"}, {"key": "Класс", "value": "Пулеметы"}, {"key": "Вес", "value": "3,11 кг"}, {"key": "Прочность", "value": "100%"}, {"key": "Макс. прочность", "value": "100%"}, {"key": "Тип боеприпасов", "value": "5.45"}, {"key": "Урон", "value": "35,1 ед"}, {"key": "Объем магазина", "value": "0/45"}, {"key": "Максимальная дистанция", "value": "150 м"}, {"key": "Скорострельность", "value": "600 выстр/мин"}, {"key": "Перезарядка", "value": "3,8 с"}, {"key": "Тактическая перезарядка", "value": "3 с"}, {"key": "Разброс", "value": "0,45°"}, {"key": "Разброс от бедра", "value": "2,45°"}, {"key": "Вертикальная отдача", "value": "0,55°"}, {"key": "Горизонтальная отдача", "value": "0,2°"}, {"key": "Доставание", "value": "1,15 с"}, {"key": "Прицеливание", "value": "0,25 с"}, {"key": "description", "value": "Ручной пулемет, разработанный для замены в войсках пулемета РПК под патрон 7.62x39 мм в рамках системы стрелкового оружия под малоимпульсный патрон 5.45x39 мм. Принят на вооружение в 1974 году вместе с автоматом АК-74."}]}