{"name": "КИМ-100 «Гранат»", "info": [{"key": "Ранг", "value": "Сталкер"}, {"key": "Класс", "value": "Научные"}, {"key": "Вес", "value": "6 кг"}, {"key": "Прочность", "value": "100%"}, {"key": "Макс. прочность", "value": "100%"}, {"key": "Переносимый вес", "value": "+6"}, {"key": "Периодическое лечение", "value": "+5%"}, {"key": "Кровотечение", "value": "-1"}, {"key": "Пулестойкость", "value": "58"}, {"key": "Защита от разрыва", "value": "29"}, {"key": "Защита от взрыва", "value": "23"}, {"key": "Электрозащита", "value": "600"}, {"key": "Защита от огня", "value": "600"}, {"key": "Химзащита", "value": "600"}, {"key": "Защита от радиации", "value": "300"}, {"key": "Защита от температуры", "value": "300"}, {"key": "Защита от биозаражения", "value": "300"}, {"key": "Защита от пси-излучения", "value": "200"}, {"key": "Защита от кровотечения", "value": "30%"}, {"key": "description", "value": "Любые"}, {"key": "description", "value": "Любые"}, {"key": "description", "value": "Научный костюм ярко красного цвета. Один из шедевров НИИ «ЧаЗ». Оснащен непревзойденной системой жизнеобеспечения."}]}